[
{ "Verses": "1 kallaththaraasu Karththarukku Aruvaruppaanadhu; Sumuththiraiyaana Niraikallo Avarukkup Piriyam. "},
{ "Verses": "2 agandhai Vandhaal Lachchaiyum Varum; Thaazhndha Sindhaiyullavargalidaththil Gnaanam Undu. "},
{ "Verses": "3 semmaiyaanavargaludaiya Uththamam Avargalai Nadaththum; Dhrogigalin Maarupaado Avargalaip Paazhaakkum. "},
{ "Verses": "4 kobaakkinai Naalil Aisuvariyam Udhavaadhu; Needhiyo Maranaththukkuth Thappuvikkum. "},
{ "Verses": "5 uththamanudaiya Needhi Avan Vazhiyai Semmaippaduththum; Dhunmaarkkano Than Dhunmaarkkaththinaal Vizhuvaan. "},
{ "Verses": "6 semmaiyaanavargaludaiya Needhi Avargalaith Thappuvikkum; Dhrogigalo Thangal Theevinaiyile Pidipaduvaargal. "},
{ "Verses": "7 dhunmaarkkan Marikkumbodhu Avan Nambikkai Azhiyum; Akkiramakkaararin Abetchai Kettuppom. "},
{ "Verses": "8 needhimaan Ikkattinindru Viduvikkappaduvaan; Avan Irundha Idaththile Dhunmaarkkan Varuvaan. "},
{ "Verses": "9 maayakkaaran Thanakku Aduththavanai Vaayinaal Kedukkiraan; Needhimaano Arivinaal Thappugiraan. "},
{ "Verses": "10 needhimaangal Nandraayirundhaal Pattanam Kalikoorum; Dhunmaarkkar Azhindhaal Gambeeram Undaagum. "},
{ "Verses": "11 semmaiyaanavargaludaiya Aaseervaadhaththinaal Pattanam Nilaipetrongum; Dhunmaarkkarudaiya Vaayinaal Adhu Idindhu Vizhum. "},
{ "Verses": "12 madhikettavan Piranai Avamadhikkiraan; Buththimaano Than Vaayai Adakkikkondirukkiraan. "},
{ "Verses": "13 purankoorith Thirigiravan Ragasiyaththai Velippaduththugiraan; Aaviyil Unmaiyullavano Kaariyaththai Adakkugiraan. "},
{ "Verses": "14 aalosanaiyillaadha Idaththil Janangal Vizhundhupovaargal; Anega Aalosanaikkaarar Undaanaal Sugam Undaagum. "},
{ "Verses": "15 anniyanukkaagap Pinaippadugiravan Vegu Paadupaduvaan; Pinaippaduvadhai Veruppavan Sugamaayiruppaan. "},
{ "Verses": "16 nallozhukkamulla Sthree Maanaththaik Kaappaal; Paraakkiramasaaligal Aisuvariyaththaik Kaappaargal. "},
{ "Verses": "17 dhayaiyulla Manushan Than Aaththumaavukku Nanmaiseydhukollugiraan; Kadoorano Than Udalai Alaikkazhikkiraan. "},
{ "Verses": "18 dhunmaarkkan Virudhaavelaiyai Seygiraan; Needhiyai Vidhaikkiravano Meyppalanaip Peruvaan. "},
{ "Verses": "19 needhi Jeevanukku Edhuvaagiradhupol Theemaiyaip Pinthodarugiravan Maranaththukku Edhuvaagiraan. "},
{ "Verses": "20 maarupaadulla Irudhayamudaiyavargal Karththarukku Aruvaruppaanavargal; Uththama Maarkkaththaaro Avarukkup Piriyamaanavargal. "},
{ "Verses": "21 kaiyode Kaikorththaalum, Dhushtan Thandanaikkuth Thappaan; Needhimaangaludaiya Sandhadhiyo Viduvikkappadum. "},
{ "Verses": "22 madhikedaai Nadakkira Azhagulla Sthree, Pandriyin Mookkilulla Pon Mookkuththikku Samaanam. "},
{ "Verses": "23 needhimaangaludaiya Aasai Nanmaiye; Dhunmaarkkarudaiya Nambikkaiyo Kobaakkinaiyaai Mudiyum. "},
{ "Verses": "24 vaariyiraiththum Viruththiyadaivaarum Undu; Adhigamaaip Pisiniththanampanniyum Varumaiyadaivaarum Undu. "},
{ "Verses": "25 udhaaragunamulla Aaththumaa Sezhikkum; Evan Thanneer Paaichchugiraano Avanukkuth Thanneer Paaichchappadum. "},
{ "Verses": "26 dhaaniyaththaik Kattivaikkiravanai Janangal Sabippaargal; Virkiravanudaiya Thalaiyinmel Aaseervaadham Thangum. "},
{ "Verses": "27 nanmaiyai Jaakkiradhaiyudan Thedugiravan Dhayaiyaip Peruvaan; Theemaiyaith Thedugiravanukko Theemaiye Varum. "},
{ "Verses": "28 than Aisuvariyaththai Nambugiravan Vizhuvaan; Needhimaangalo Thuliraippole Thazhaippaargal. "},
{ "Verses": "29 than Veettaik Kalaikkiravan Kaatrai Sudhandharippaan; Moodan Gnaanamullavanukku Adimaiyaavaan. "},
{ "Verses": "30 needhimaanudaiya Balan Jeevavirutcham; Aaththumaakkalai Aadhaayappaduththikkollugiravan Gnaanamullavan. "},
{ "Verses": "31 idho, Needhimaanukku Boomiyil Sarikkattappadume; Dhunmaarkkanukkum Paavikkum Eththanai Adhigam. "}
]